deterministic.cpython-37m-darwin.so
pyrossgeo/Simulation.cpp
pyrossgeo/Simulation.cpython-37m-darwin.so
pyrossgeo/Simulation.pxd
pyrossgeo/Simulation.pyx
pyrossgeo/__defs__.c
pyrossgeo/__defs__.cpython-37m-darwin.so
pyrossgeo/__defs__.pxd
pyrossgeo/__defs__.pyx
pyrossgeo/__init__.py
pyrossgeo/_helpers.c
pyrossgeo/_helpers.cpython-37m-darwin.so
pyrossgeo/_helpers.pyx
pyrossgeo/_initialization.c
pyrossgeo/_initialization.cpython-37m-darwin.so
pyrossgeo/_initialization.pyx
pyrossgeo/_simulation.cpp
pyrossgeo/_simulation.cpython-37m-darwin.so
pyrossgeo/_simulation.pxd
pyrossgeo/_simulation.pyx
pyrossgeo/utils.py
pyrossgeo/mft/__init__.py
pyrossgeo/mft/deterministic.c
pyrossgeo/mft/deterministic.cpython-37m-darwin.so
pyrossgeo/mft/deterministic.pyx
pyrossgeo/pyrossgeo/Simulation.cpython-37m-darwin.so
pyrossgeo/pyrossgeo/__defs__.cpython-37m-darwin.so
pyrossgeo/pyrossgeo/_helpers.cpython-37m-darwin.so
pyrossgeo/pyrossgeo/_initialization.cpython-37m-darwin.so
pyrossgeo/pyrossgeo/_simulation.cpython-37m-darwin.so
pyrossgeo/pyrossgeo/mft/deterministic.cpython-37m-darwin.so
pyrossgeo-1.0.8.dist-info/LICENSE
pyrossgeo-1.0.8.dist-info/METADATA
pyrossgeo-1.0.8.dist-info/WHEEL
pyrossgeo-1.0.8.dist-info/top_level.txt
pyrossgeo-1.0.8.dist-info/RECORD
