Metadata-Version: 2.1
Name: pyrossgeo
Version: 1.0.8
Summary: PyRossGeo is a python library for spatially resolved numerical simulation of infectious diseases
Home-page: https://github.com/lukastk/PyRossGeo.git
Author: The PyRossGeo team
License: MIT
Project-URL: Documentation, https://pyrossgeo.readthedocs.io
Project-URL: Source, https://github.com/lukastk/PyRossGeo.git
Platform: works on all platforms (such as LINUX
Platform: macOS
Platform: and Microsoft Windows)
Classifier: License :: OSI Approved :: MIT License
Classifier: Programming Language :: Python :: 3
Classifier: Programming Language :: Python :: 3.7
Classifier: Topic :: Scientific/Engineering
Classifier: Topic :: Scientific/Engineering :: Mathematics
Classifier: Intended Audience :: Science/Research
Classifier: Intended Audience :: Education
Requires-Dist: cython
Requires-Dist: numpy
Requires-Dist: scipy
Requires-Dist: matplotlib
Requires-Dist: pandas
Requires-Dist: zarr
Requires-Dist: geopandas
